cifparser/__init__.py
cifparser/converters.py
cifparser/errors.py
cifparser/grammar.py
cifparser/namespace.py
cifparser/parser.py
cifparser/path.py
cifparser/valuetree.py
cifparser/version.py
cifparser-0.0.2.dist-info/DESCRIPTION.rst
cifparser-0.0.2.dist-info/METADATA
cifparser-0.0.2.dist-info/metadata.json
cifparser-0.0.2.dist-info/RECORD
cifparser-0.0.2.dist-info/top_level.txt
cifparser-0.0.2.dist-info/WHEEL
