Metadata-Version: 2.0
Name: cifparser
Version: 0.0.2
Summary: CIF (Configuration Interchange Format) parser
Home-page: https://github.com/msfrank/cifparser
Author: Michael Frank
Author-email: msfrank@syntaxockey.com
License: UNKNOWN
Platform: UNKNOWN
Classifier: Development Status :: 3 - Alpha
Classifier: Intended Audience :: Developers
Classifier: License :: OSI Approved :: BSD License
Classifier: Natural Language :: English
Classifier: Programming Language :: Python :: 3
Requires-Dist: pyparsing
